mcp_vms.py
mcp_vms_config.py
vmspy.py
iflow_mcp_jyjune_mcp_vms-0.1.0.dist-info/METADATA
iflow_mcp_jyjune_mcp_vms-0.1.0.dist-info/WHEEL
iflow_mcp_jyjune_mcp_vms-0.1.0.dist-info/entry_points.txt
iflow_mcp_jyjune_mcp_vms-0.1.0.dist-info/licenses/LICENSE
iflow_mcp_jyjune_mcp_vms-0.1.0.dist-info/RECORD
