Metadata-Version: 2.4
Name: iflow-mcp_jyjune_mcp-vms
Version: 0.1.0
Summary: VMS Video Fetch
License-File: LICENSE
Requires-Python: >=3.11
Requires-Dist: mcp[cli]>=1.2.1
Requires-Dist: numpy>=2.2.4
Requires-Dist: pillow>=11.1.0
